color_extract/__init__.py
color_extract/cli.py
color_extract/core.py
color_extract/utils.py
color_extract/visualization.py
color_extract-0.0.3.dist-info/LICENSE
color_extract-0.0.3.dist-info/METADATA
color_extract-0.0.3.dist-info/WHEEL
color_extract-0.0.3.dist-info/entry_points.txt
color_extract-0.0.3.dist-info/top_level.txt
color_extract-0.0.3.dist-info/RECORD
