Metadata-Version: 2.1
Name: color-extract
Version: 0.0.3
Summary: Extract dominant colors from images using various K-Means clustering approaches
Author: Bruno Imbrizi
License: MIT
Project-URL: Homepage, https://github.com/brunoimbrizi/color-extract
Project-URL: Documentation, https://github.com/brunoimbrizi/color-extract#readme
Project-URL: Repository, https://github.com/brunoimbrizi/color-extract.git
Project-URL: Bug Tracker, https://github.com/brunoimbrizi/color-extract/issues
Keywords: color,color-extraction,dominant-colors,palette,image-processing,kmeans,clustering,touchdesigner
Classifier: Development Status :: 5 - Production/Stable
Classifier: Intended Audience :: Developers
Classifier: Topic :: Multimedia :: Graphics
Classifier: Topic :: Multimedia :: Graphics :: Graphics Conversion
Classifier: Topic :: Software Development :: Libraries :: Python Modules
Classifier: Topic :: Scientific/Engineering :: Image Processing
Classifier: Programming Language :: Python :: 3
Classifier: Programming Language :: Python :: 3.7
Classifier: Programming Language :: Python :: 3.8
Classifier: Programming Language :: Python :: 3.9
Classifier: Programming Language :: Python :: 3.10
Classifier: Programming Language :: Python :: 3.11
Classifier: Programming Language :: Python :: 3.12
Classifier: Operating System :: OS Independent
Requires-Python: >=3.7
License-File: LICENSE
Requires-Dist: numpy>=1.19.0
Requires-Dist: scikit-learn>=0.24.0
Requires-Dist: scikit-image>=0.18.0
Requires-Dist: Pillow>=8.0.0
Provides-Extra: dev
Requires-Dist: pytest>=6.0; extra == "dev"
Requires-Dist: pytest-cov>=2.0; extra == "dev"
Requires-Dist: black>=21.0; extra == "dev"
Requires-Dist: flake8>=3.9; extra == "dev"
Requires-Dist: mypy>=0.900; extra == "dev"
Requires-Dist: twine>=3.4; extra == "dev"
Requires-Dist: wheel>=0.36; extra == "dev"
Requires-Dist: build>=0.7; extra == "dev"
